hlfiles/__init__.py
hlfiles/convert.py
hlfiles/read.py
hlfiles-0.0.1.dist-info/METADATA
hlfiles-0.0.1.dist-info/WHEEL
hlfiles-0.0.1.dist-info/top_level.txt
hlfiles-0.0.1.dist-info/RECORD
