Metadata-Version: 2.1
Name: hlfiles
Version: 0.0.1
Summary: Handle lots of files
Home-page: https://github.com/UePG-21/hlfiles
Author: UePG
Author-email: hanlin.warng@gmail.com
License: MIT
Classifier: Programming Language :: Python :: 3
Classifier: License :: OSI Approved :: MIT License
Classifier: Operating System :: OS Independent
